agisdk/__init__.py
agisdk/real/__init__.py
agisdk/real/harness.py
agisdk/real/browsergym/__init__.py
agisdk/real/browsergym/core/__init__.py
agisdk/real/browsergym/core/chat.py
agisdk/real/browsergym/core/constants.py
agisdk/real/browsergym/core/env.py
agisdk/real/browsergym/core/observation.py
agisdk/real/browsergym/core/registration.py
agisdk/real/browsergym/core/spaces.py
agisdk/real/browsergym/core/task.py
agisdk/real/browsergym/core/action/__init__.py
agisdk/real/browsergym/core/action/base.py
agisdk/real/browsergym/core/action/functions.py
agisdk/real/browsergym/core/action/highlevel.py
agisdk/real/browsergym/core/action/openai_cua.py
agisdk/real/browsergym/core/action/parsers.py
agisdk/real/browsergym/core/action/python.py
agisdk/real/browsergym/core/action/utils.py
agisdk/real/browsergym/experiments/__init__.py
agisdk/real/browsergym/experiments/agent.py
agisdk/real/browsergym/experiments/loop.py
agisdk/real/browsergym/experiments/utils.py
agisdk/real/browsergym/utils/__init__.py
agisdk/real/browsergym/utils/obs.py
agisdk/real/browsergym/webclones/__init__.py
agisdk/real/browsergym/webclones/base.py
agisdk/real/browsergym/webclones/evaluate.py
agisdk/real/browsergym/webclones/task_config.py
agisdk/real/browsergym/webclones/utils.py
agisdk/real/demo_agent/__init__.py
agisdk/real/demo_agent/basic_agent.py
agisdk/real/demo_agent/run_demo.py
agisdk-0.1.1.dist-info/METADATA
agisdk-0.1.1.dist-info/WHEEL
agisdk-0.1.1.dist-info/top_level.txt
agisdk-0.1.1.dist-info/RECORD
