Metadata-Version: 2.4
Name: agisdk
Version: 0.1.1
Summary: AGI SDK - tools for building and evaluating AI web agents
Author-email: Diego Caples <diego@theagi.company>
Project-URL: Homepage, https://github.com/agi-inc/agisdk
Project-URL: Bug Tracker, https://github.com/agi-inc/agisdk/issues
Project-URL: Documentation, https://github.com/agi-inc/agisdk
Project-URL: Leaderboard, https://realevals.xyz
Classifier: Programming Language :: Python :: 3
Classifier: License :: OSI Approved :: MIT License
Classifier: Operating System :: OS Independent
Classifier: Development Status :: 4 - Beta
Classifier: Intended Audience :: Developers
Classifier: Intended Audience :: Science/Research
Classifier: Topic :: Scientific/Engineering :: Artificial Intelligence
Requires-Python: >=3.9
Requires-Dist: numpy>=1.20.0
Requires-Dist: pillow>=8.0.0
Requires-Dist: gymnasium>=0.28.0
Requires-Dist: playwright>=1.20.0
Requires-Dist: tqdm>=4.62.0
Requires-Dist: python-dotenv>=0.19.0
Requires-Dist: openai>=1.0.0
Requires-Dist: requests>=2.25.0
